argostranslate/__init__.py
argostranslate/apis.py
argostranslate/apply_bpe.py
argostranslate/argospm.py
argostranslate/cli.py
argostranslate/fewshot.py
argostranslate/models.py
argostranslate/networking.py
argostranslate/package.py
argostranslate/sbd.py
argostranslate/settings.py
argostranslate/tags.py
argostranslate/tokenizer.py
argostranslate/translate.py
argostranslate/utils.py
argostranslatemain-1.9.7.data/scripts/argos-translate
argostranslatemain-1.9.7.data/scripts/argospm
argostranslatemain-1.9.7.dist-info/licenses/LICENSE
tests/__init__.py
tests/test_english_translations.py
tests/test_package.py
tests/test_translate.py
argostranslatemain-1.9.7.dist-info/METADATA
argostranslatemain-1.9.7.dist-info/WHEEL
argostranslatemain-1.9.7.dist-info/top_level.txt
argostranslatemain-1.9.7.dist-info/RECORD
