Metadata-Version: 2.4
Name: argostranslatemain
Version: 1.9.7
Summary: Open-source neural machine translation library based on OpenNMT's CTranslate2
Home-page: https://www.argosopentech.com
Author: Argos Open Technologies, LLC
Author-email: admin@argosopentech.com
Project-URL: Website, https://www.argosopentech.com
Project-URL: Documentation, https://argos-translate.readthedocs.io/en/latest/
Project-URL: GitHub, https://github.com/argosopentech/argos-translate
Project-URL: Forum, https://community.libretranslate.com/c/argos-translate/5
Classifier: License :: OSI Approved :: MIT License
Classifier: Programming Language :: Python :: 3
Classifier: Development Status :: 5 - Production/Stable
Requires-Python: >=3.5
License-File: LICENSE
Requires-Dist: ctranslate2<5,>=4.0
Requires-Dist: sentencepiece==0.2.0
Requires-Dist: stanza==1.1.1
Requires-Dist: packaging
Requires-Dist: sacremoses==0.0.53
Dynamic: author
Dynamic: author-email
Dynamic: classifier
Dynamic: description
Dynamic: description-content-type
Dynamic: home-page
Dynamic: license-file
Dynamic: project-url
Dynamic: requires-dist
Dynamic: requires-python
Dynamic: summary
